[
  {
    "id": "1",
    "position": { "x": 100, "y": 50 },
    "data": {
      "label": "Lectura y escritura académica",
      "status": "Pendiente",
      "weeklyHours": 5,
      "credits": 10,
      "prerequisites": [],
      "degreeModule": "Ciclo Introductorio"
    },
    "type": "custom"
  },
  {
    "id": "2",
    "position": { "x": 100, "y": 50 },
    "data": {
      "label": "Matemática",
      "status": "Pendiente",
      "weeklyHours": 5,
      "credits": 10,
      "prerequisites": [],
      "degreeModule": "Ciclo Introductorio"
    },
    "type": "custom"
  },
  {
    "id": "3",
    "position": { "x": 100, "y": 50 },
    "data": {
      "label": "Elementos de programación y lógica",
      "status": "Pendiente",
      "weeklyHours": 5,
      "credits": 10,
      "prerequisites": [],
      "degreeModule": "Ciclo Introductorio"
    },
    "type": "custom"
  },
  {
    "id": "4",
    "position": { "x": 100, "y": 50 },
    "data": {
      "label": "Introducción a la Programación",
      "status": "Pendiente",
      "weeklyHours": 8,
      "credits": 16,
      "prerequisites": ["Elementos de programación y lógica"],
      "degreeModule": "Núcleo básico obligatorio"
    },
    "type": "custom"
  },
  {
    "id": "5",
    "position": { "x": 100, "y": 50 },
    "data": {
      "label": "Organización de Computadoras",
      "status": "Pendiente",
      "weeklyHours": 6,
      "credits": 12,
      "prerequisites": ["Elementos de programación y lógica"],
      "degreeModule": "Núcleo básico obligatorio"
    },
    "type": "custom"
  },
  {
    "id": "6",
    "position": { "x": 100, "y": 50 },
    "data": {
      "label": "Matemática I",
      "status": "Pendiente",
      "weeklyHours": 8,
      "credits": 16,
      "prerequisites": ["Elementos de programación y lógica", "Matemática"],
      "degreeModule": "Núcleo básico obligatorio"
    },
    "type": "custom"
  },
  {
    "id": "7",
    "position": { "x": 100, "y": 50 },
    "data": {
      "label": "Programación con Objetos I",
      "status": "Pendiente",
      "weeklyHours": 8,
      "credits": 16,
      "prerequisites": ["Introducción a la Programación"],
      "degreeModule": "Núcleo básico obligatorio"
    },
    "type": "custom"
  },
  {
    "id": "8",
    "position": { "x": 100, "y": 50 },
    "data": {
      "label": "Bases de Datos",
      "status": "Pendiente",
      "weeklyHours": 6,
      "credits": 12,
      "prerequisites": [],
      "degreeModule": "Núcleo básico obligatorio"
    },
    "type": "custom"
  },
  {
    "id": "9",
    "position": { "x": 100, "y": 50 },
    "data": {
      "label": "Estructuras de Datos",
      "status": "Pendiente",
      "weeklyHours": 8,
      "credits": 16,
      "prerequisites": ["Introducción a la Programación"],
      "degreeModule": "Núcleo básico obligatorio"
    },
    "type": "custom"
  },
  {
    "id": "10",
    "position": { "x": 100, "y": 50 },
    "data": {
      "label": "Programación con Objetos II",
      "status": "Pendiente",
      "weeklyHours": 6,
      "credits": 12,
      "prerequisites": ["Programación con Objetos I"],
      "degreeModule": "Núcleo básico obligatorio"
    },
    "type": "custom"
  },
  {
    "id": "11",
    "position": { "x": 100, "y": 50 },
    "data": {
      "label": "Redes de Computadoras",
      "status": "Pendiente",
      "weeklyHours": 6,
      "credits": 12,
      "prerequisites": ["Organización de Computadoras"],
      "degreeModule": "Núcleo avanzado obligatorio"
    },
    "type": "custom"
  },
  {
    "id": "12",
    "position": { "x": 100, "y": 50 },
    "data": {
      "label": "Sistemas Operativos",
      "status": "Pendiente",
      "weeklyHours": 6,
      "credits": 12,
      "prerequisites": [
        "Introducción a la Programación",
        "Organización de Computadoras"
      ],
      "degreeModule": "Núcleo avanzado obligatorio"
    },
    "type": "custom"
  },
  {
    "id": "13",
    "position": { "x": 100, "y": 50 },
    "data": {
      "label": "Programación Concurrente",
      "status": "Pendiente",
      "weeklyHours": 4,
      "credits": 8,
      "prerequisites": ["Estructuras de Datos"],
      "degreeModule": "Núcleo avanzado obligatorio"
    },
    "type": "custom"
  },
  {
    "id": "14",
    "position": { "x": 100, "y": 50 },
    "data": {
      "label": "Matemática II",
      "status": "Pendiente",
      "weeklyHours": 4,
      "credits": 8,
      "prerequisites": ["Matemática I"],
      "degreeModule": "Núcleo avanzado obligatorio"
    },
    "type": "custom"
  },
  {
    "id": "15",
    "position": { "x": 100, "y": 50 },
    "data": {
      "label": "Elementos de Ingeniería de Software",
      "status": "Pendiente",
      "weeklyHours": 6,
      "credits": 12,
      "prerequisites": ["Programación con Objetos II"],
      "degreeModule": "Núcleo avanzado obligatorio"
    },
    "type": "custom"
  },
  {
    "id": "16",
    "position": { "x": 100, "y": 50 },
    "data": {
      "label": "Construcción de Interfaces de Usuario",
      "status": "Pendiente",
      "weeklyHours": 6,
      "credits": 12,
      "prerequisites": ["Programación con Objetos II"],
      "degreeModule": "Núcleo avanzado obligatorio"
    },
    "type": "custom"
  },
  {
    "id": "17",
    "position": { "x": 100, "y": 50 },
    "data": {
      "label": "Estrategias de Persistencia",
      "status": "Pendiente",
      "weeklyHours": 6,
      "credits": 12,
      "prerequisites": ["Base de Datos", "Programación con Objetos II"],
      "degreeModule": "Núcleo avanzado obligatorio"
    },
    "type": "custom"
  },
  {
    "id": "18",
    "position": { "x": 100, "y": 50 },
    "data": {
      "label": "Programación Funcional",
      "status": "Pendiente",
      "weeklyHours": 4,
      "credits": 8,
      "prerequisites": ["Estructuras de Datos"],
      "degreeModule": "Núcleo avanzado obligatorio"
    },
    "type": "custom"
  },
  {
    "id": "19",
    "position": { "x": 100, "y": 50 },
    "data": {
      "label": "Desarrollo de Aplicaciones",
      "status": "Pendiente",
      "weeklyHours": 6,
      "credits": 12,
      "prerequisites": [
        "Construcción de Interfaces de Usuario",
        "Elementos de Ingeniería de Software",
        "Estrategias de Persistencia"
      ],
      "degreeModule": "Núcleo avanzado obligatorio"
    },
    "type": "custom"
  },
  {
    "id": "20",
    "position": { "x": 100, "y": 50 },
    "data": {
      "label": "Laboratorio de Sistemas Operativos y Redes",
      "status": "Pendiente",
      "weeklyHours": 4,
      "credits": 8,
      "prerequisites": ["Sistemas Operativos", "Redes de Computadoras"],
      "degreeModule": "Núcleo avanzado obligatorio"
    },
    "type": "custom"
  },
  {
    "id": "21",
    "position": { "x": 100, "y": 50 },
    "data": {
      "label": "Seguridad Informática",
      "status": "Pendiente",
      "weeklyHours": 4,
      "credits": 8,
      "prerequisites": [],
      "degreeModule": "Núcleo Complementario"
    },
    "type": "custom"
  },
  {
    "id": "22",
    "position": { "x": 100, "y": 50 },
    "data": {
      "label": "Bases de Datos II",
      "status": "Pendiente",
      "weeklyHours": 4,
      "credits": 8,
      "prerequisites": [],
      "degreeModule": "Núcleo Complementario"
    },
    "type": "custom"
  },
  {
    "id": "23",
    "position": { "x": 100, "y": 50 },
    "data": {
      "label": "Participación y Gestión en Proyectos de Software Libre",
      "status": "Pendiente",
      "weeklyHours": 4,
      "credits": 8,
      "prerequisites": [],
      "degreeModule": "Núcleo Complementario"
    },
    "type": "custom"
  },
  {
    "id": "24",
    "position": { "x": 100, "y": 50 },
    "data": {
      "label": "Introducción a las Arquitecturas de Software",
      "status": "Pendiente",
      "weeklyHours": 4,
      "credits": 8,
      "prerequisites": [],
      "degreeModule": "Núcleo Complementario"
    },
    "type": "custom"
  },
  {
    "id": "25",
    "position": { "x": 100, "y": 50 },
    "data": {
      "label": "Programación con Objetos III",
      "status": "Pendiente",
      "weeklyHours": 4,
      "credits": 8,
      "prerequisites": [],
      "degreeModule": "Núcleo Complementario"
    },
    "type": "custom"
  },
  {
    "id": "26",
    "position": { "x": 100, "y": 50 },
    "data": {
      "label": "Introducción a la Bioinformática",
      "status": "Pendiente",
      "weeklyHours": 4,
      "credits": 8,
      "prerequisites": [],
      "degreeModule": "Núcleo Complementario"
    },
    "type": "custom"
  },
  {
    "id": "27",
    "position": { "x": 100, "y": 50 },
    "data": {
      "label": "Políticas Públicas en la Sociedad de la Información y la Era Digital",
      "status": "Pendiente",
      "weeklyHours": 4,
      "credits": 8,
      "prerequisites": [],
      "degreeModule": "Núcleo Complementario"
    },
    "type": "custom"
  },
  {
    "id": "28",
    "position": { "x": 100, "y": 50 },
    "data": {
      "label": "Sistemas de Información Geográfica",
      "status": "Pendiente",
      "weeklyHours": 4,
      "credits": 8,
      "prerequisites": [],
      "degreeModule": "Núcleo Complementario"
    },
    "type": "custom"
  },
  {
    "id": "29",
    "position": { "x": 100, "y": 50 },
    "data": {
      "label": "Herramientas Declarativas en Programación",
      "status": "Pendiente",
      "weeklyHours": 4,
      "credits": 8,
      "prerequisites": [],
      "degreeModule": "Núcleo Complementario"
    },
    "type": "custom"
  },
  {
    "id": "30",
    "position": { "x": 100, "y": 50 },
    "data": {
      "label": "Introducción al Desarrollo de Videojuegos",
      "status": "Pendiente",
      "weeklyHours": 4,
      "credits": 8,
      "prerequisites": [],
      "degreeModule": "Núcleo Complementario"
    },
    "type": "custom"
  },
  {
    "id": "31",
    "position": { "x": 100, "y": 50 },
    "data": {
      "label": "Derechos de Autor y Derechos de Copia en la Era Digital",
      "status": "Pendiente",
      "weeklyHours": 4,
      "credits": 8,
      "prerequisites": [],
      "degreeModule": "Núcleo Complementario"
    },
    "type": "custom"
  },
  {
    "id": "32",
    "position": { "x": 100, "y": 50 },
    "data": {
      "label": "Seminarios",
      "status": "Pendiente",
      "weeklyHours": 4,
      "credits": 8,
      "prerequisites": [],
      "degreeModule": "Núcleo Complementario"
    },
    "type": "custom"
  },
  {
    "id": "33",
    "position": { "x": 100, "y": 50 },
    "data": {
      "label": "Seminarios sobre Herramientas o Técnicas Puntuales",
      "status": "Pendiente",
      "weeklyHours": 4,
      "credits": 8,
      "prerequisites": [],
      "degreeModule": "Núcleo Complementario"
    },
    "type": "custom"
  }
]
